<?xml version='1.0' encoding='UTF-8'?>
<L5RCM>
  <School clanid="monkey" name="Toku Bushi School" id="monkey_toku_bushi_school">
    <Trait>willpower</Trait>
    <Honor>5.5</Honor>
    <Tags>
      <Tag>bushi</Tag>
      <Tag>monkey_bushi</Tag>
    </Tags>
    <Skills>
      <Skill id="athletics" rank="1"/>
      <Skill id="defense" rank="1"/>
      <Skill id="hunting" rank="1"/>
      <Skill rank="1" id="investigation" emphases="Search"/>
      <Skill id="kenjutsu" rank="1"/>
      <Skill id="lore_history" rank="1"/>
      <PlayerChoose rank="1">
        <Wildcard>bugei</Wildcard>
        <Wildcard>high</Wildcard>
      </PlayerChoose>
    </Skills>
    <Spells/>
    <Techs>
      <Tech name="Toku's Lesson" rank="1" id="monkey_tokus_lesson"></Tech>
      <Tech name="The Strength Of One Man" rank="2" id="monkey_the_strength_of_one_man"></Tech>
      <Tech name="Courage Above All" rank="3" id="monkey_courage_above_all"></Tech>
      <Tech name="Forge Your Own Fate" rank="4" id="monkey_forge_your_own_fate"></Tech>
      <Tech name="Fortune Favors The Mortal Man" rank="5" id="monkey_fortune_favors_the_mortal_man"></Tech>
    </Techs>
    <Requirements/>
  </School>
</L5RCM>
